streamlit_deeplinker/__init__.py
streamlit_deeplinker/router.py
streamlit_deeplinker-0.1.2.dist-info/LICENCE
streamlit_deeplinker-0.1.2.dist-info/METADATA
streamlit_deeplinker-0.1.2.dist-info/WHEEL
streamlit_deeplinker-0.1.2.dist-info/RECORD
