Metadata-Version: 2.1
Name: streamlit-deeplinker
Version: 0.1.2
Summary: A package that makes it possible to add deeplinks in a streamlit application
Author: Mats E. Mollestad
Author-email: mats@mollestad.no
Requires-Python: >=3.10,<4.0
Classifier: Programming Language :: Python :: 3
Classifier: Programming Language :: Python :: 3.10
Classifier: Programming Language :: Python :: 3.11
Classifier: Programming Language :: Python :: 3.12
Requires-Dist: pydantic (>=2.7.0,<3.0.0)
Requires-Dist: streamlit (>=1.33.0,<2.0.0)
